regal/__init__.py
regal/check_interface.py
regal/control.py
regal/format.py
regal/grouping.py
regal/tools.py
regal-1.3.dist-info/.DS_Store
regal-1.3.dist-info/LICENSE
regal-1.3.dist-info/METADATA
regal-1.3.dist-info/WHEEL
regal-1.3.dist-info/top_level.txt
regal-1.3.dist-info/RECORD
